streamlit_gov_uk_components/__init__.py
streamlit_gov_uk_components/frontend_checkbox/build/asset-manifest.json
streamlit_gov_uk_components/frontend_checkbox/build/govuk-frontend-4.0.0.min.css
streamlit_gov_uk_components/frontend_checkbox/build/index.html
streamlit_gov_uk_components/frontend_checkbox/build/static/js/main.f177d2c4.js
streamlit_gov_uk_components/frontend_checkbox/build/static/js/main.f177d2c4.js.LICENSE.txt
streamlit_gov_uk_components/frontend_checkbox/build/static/js/main.f177d2c4.js.map
streamlit_gov_uk_components/frontend_checkbox_list/build/asset-manifest.json
streamlit_gov_uk_components/frontend_checkbox_list/build/govuk-frontend-4.0.0.min.css
streamlit_gov_uk_components/frontend_checkbox_list/build/index.html
streamlit_gov_uk_components/frontend_checkbox_list/build/static/js/main.0481c9e7.js
streamlit_gov_uk_components/frontend_checkbox_list/build/static/js/main.0481c9e7.js.LICENSE.txt
streamlit_gov_uk_components/frontend_checkbox_list/build/static/js/main.0481c9e7.js.map
streamlit_gov_uk_components/frontend_checkbox_small/build/asset-manifest.json
streamlit_gov_uk_components/frontend_checkbox_small/build/govuk-frontend-4.0.0.min.css
streamlit_gov_uk_components/frontend_checkbox_small/build/index.html
streamlit_gov_uk_components/frontend_checkbox_small/build/static/js/main.f129773e.js
streamlit_gov_uk_components/frontend_checkbox_small/build/static/js/main.f129773e.js.LICENSE.txt
streamlit_gov_uk_components/frontend_checkbox_small/build/static/js/main.f129773e.js.map
streamlit_gov_uk_components/frontend_checkbox_small_list/build/asset-manifest.json
streamlit_gov_uk_components/frontend_checkbox_small_list/build/govuk-frontend-4.0.0.min.css
streamlit_gov_uk_components/frontend_checkbox_small_list/build/index.html
streamlit_gov_uk_components/frontend_checkbox_small_list/build/static/js/main.8ca85027.js
streamlit_gov_uk_components/frontend_checkbox_small_list/build/static/js/main.8ca85027.js.LICENSE.txt
streamlit_gov_uk_components-0.0.14.dist-info/LICENSE
streamlit_gov_uk_components-0.0.14.dist-info/METADATA
streamlit_gov_uk_components-0.0.14.dist-info/WHEEL
streamlit_gov_uk_components-0.0.14.dist-info/top_level.txt
streamlit_gov_uk_components-0.0.14.dist-info/RECORD
