Metadata-Version: 2.1
Name: streamlit-gov-uk-components
Version: 0.0.14
Summary: A collection of Streamlit components that use or are inspired by the GOV.UK Design System
Home-page: https://github.com/uktrade/streamlit-gov-uk-components
Author: Department for International Trade
Author-email: sre@digital.trade.gov.uk
License: UNKNOWN
Platform: UNKNOWN
Classifier: Programming Language :: Python :: 3
Classifier: License :: OSI Approved :: MIT License
Classifier: Topic :: System :: Archiving :: Compression
Requires-Python: >=3.7.4
License-File: LICENSE
Requires-Dist: streamlit (>=1.3.1)
